booking_ui/__init__.py
booking_ui/apps.py
booking_ui/conf.py
booking_ui/forms.py
booking_ui/urls.py
booking_ui/utils.py
booking_ui/views.py
booking_ui/static/booking_ui/base.css
booking_ui/templates/booking_ui/base.html
booking_ui/templates/booking_ui/confirm.html
booking_ui/templates/booking_ui/portal_detail.html
booking_ui/templates/booking_ui/portal_lookup.html
booking_ui/templates/booking_ui/reschedule.html
booking_ui/templates/booking_ui/schedule.html
booking_ui/templates/booking_ui/service_detail.html
booking_ui/templates/booking_ui/services_list.html
booking_ui/templates/booking_ui/success.html
booking_ui/tests/__init__.py
booking_ui/tests/__main__.py
booking_ui/tests/models.py
booking_ui/tests/test_views.py
booking_ui/tests/utils.py
django_booking_ui-0.1.0.dist-info/licenses/LICENSE
django_booking_ui-0.1.0.dist-info/METADATA
django_booking_ui-0.1.0.dist-info/WHEEL
django_booking_ui-0.1.0.dist-info/top_level.txt
django_booking_ui-0.1.0.dist-info/RECORD
