Metadata-Version: 2.4
Name: django-booking-ui
Version: 0.1.0
Summary: Public booking pages and a lightweight customer portal for Django bookings.
Author-email: Kevin Oudai <kevin@mroudai.com>
License: MIT License
Project-URL: Homepage, https://github.com/Kevin-Oudai/django-booking-ui
Project-URL: Repository, https://github.com/Kevin-Oudai/django-booking-ui.git
Classifier: Development Status :: 3 - Alpha
Classifier: Framework :: Django
Classifier: Framework :: Django :: 4.2
Classifier: Framework :: Django :: 5.0
Classifier: License :: OSI Approved :: MIT License
Classifier: Programming Language :: Python
Classifier: Programming Language :: Python :: 3
Classifier: Programming Language :: Python :: 3.10
Classifier: Programming Language :: Python :: 3.11
Classifier: Programming Language :: Python :: 3.12
Classifier: Environment :: Web Environment
Requires-Python: >=3.10
License-File: LICENSE
Requires-Dist: Django>=4.2
Dynamic: license-file
